nwrapy/__init__.py
nwrapy/__main__.py
nwrapy/colours.py
nwrapy/csv_conv.py
nwrapy/db.py
nwrapy/get_ip.py
nwrapy/interactive.py
nwrapy/nmap_db.py
nwrapy/nmap_wrapper.py
nwrapy/read.py
nwrapy/table.py
nwrapy/utils.py
nwrapy/xml_parser.py
nwrapy-0.1.5.dist-info/LICENSE
nwrapy-0.1.5.dist-info/METADATA
nwrapy-0.1.5.dist-info/WHEEL
nwrapy-0.1.5.dist-info/entry_points.txt
nwrapy-0.1.5.dist-info/top_level.txt
nwrapy-0.1.5.dist-info/RECORD
