Metadata-Version: 2.1
Name: nwrapy
Version: 0.1.5
Summary: Nmap wrapper
Home-page: https://github.com/SneakyBeagle/nwrapy
Author: Jochem Stevense
Author-email: 
License: GPLv3
Project-URL: Bug Tracker, https://github.com/SneakyBeagle/nwrapy/issues
Platform: UNKNOWN
Classifier: Programming Language :: Python :: 3
Requires-Python: >=3.6
License-File: LICENSE
